sap_file_modifier/__init__.py
sap_file_modifier/cli.py
sap_file_modifier/modifier.py
sap_file_modifier/service.py
sapgui_shortcut_fixer_macos-0.1.0.dist-info/licenses/LICENSE
sapgui_shortcut_fixer_macos-0.1.0.dist-info/METADATA
sapgui_shortcut_fixer_macos-0.1.0.dist-info/WHEEL
sapgui_shortcut_fixer_macos-0.1.0.dist-info/entry_points.txt
sapgui_shortcut_fixer_macos-0.1.0.dist-info/top_level.txt
sapgui_shortcut_fixer_macos-0.1.0.dist-info/RECORD
