Metadata-Version: 2.4
Name: sapgui-shortcut-fixer-macos
Version: 0.1.0
Summary: Automatically fix SAP GUI shortcut files (.sap) on macOS by removing malformed /M/ parameters from GuiParm connection strings
Author-email: Nicolas Renkamp <nico.re@gmail.com>
License: MIT
Project-URL: Homepage, https://github.com/nicornk/sapgui-shortcut-fixer-macos
Project-URL: Repository, https://github.com/nicornk/sapgui-shortcut-fixer-macos
Classifier: Development Status :: 3 - Alpha
Classifier: Intended Audience :: End Users/Desktop
Classifier: Topic :: Utilities
Classifier: License :: OSI Approved :: MIT License
Classifier: Programming Language :: Python :: 3
Classifier: Programming Language :: Python :: 3.10
Classifier: Programming Language :: Python :: 3.11
Classifier: Programming Language :: Python :: 3.12
Classifier: Operating System :: MacOS :: MacOS X
Requires-Python: >=3.10
License-File: LICENSE
Provides-Extra: dev
Requires-Dist: pytest>=7.0.0; extra == "dev"
Dynamic: license-file
